scrapemed/__init__.py
scrapemed/_clean.py
scrapemed/_morehtml.py
scrapemed/_parse.py
scrapemed/_text.py
scrapemed/_validate.py
scrapemed/paper.py
scrapemed/paperSet.py
scrapemed/scrape.py
scrapemed/trees.py
scrapemed/utils.py
scrapemed/data/DTDs/nlm-articleset-2.0.dtd
scrapemed-1.1.3.dist-info/LICENSE
scrapemed-1.1.3.dist-info/METADATA
scrapemed-1.1.3.dist-info/WHEEL
scrapemed-1.1.3.dist-info/top_level.txt
scrapemed-1.1.3.dist-info/RECORD
