Metadata-Version: 2.1
Name: scrapemed
Version: 1.1.3
Summary: Data Scraping for PubMed Central.
Author-email: Daniel Frees <danielfrees@g.ucla.edu>
Project-URL: Homepage, https://github.com/danielfrees/scrapemed/
Project-URL: Bug Tracke, https://github.com/danielfrees/scrapemed/issues
Classifier: Development Status :: 4 - Beta
Classifier: Intended Audience :: Developers
Classifier: License :: OSI Approved :: MIT License
Classifier: Programming Language :: Python :: 3
Classifier: Programming Language :: Python :: 3.11
Requires-Python: >=3.11
License-File: LICENSE
Requires-Dist: biopython >=1.78
Requires-Dist: graphviz >=0.20.1
Requires-Dist: lxml ==4.9.0
Requires-Dist: pandas >=1.5.2
Requires-Dist: requests-html >=0.10.0
Requires-Dist: sqlalchemy >=1.4.39
Requires-Dist: beautifulsoup4 >=4.11
Requires-Dist: html5lib >=1.1
Requires-Dist: jinja2
Requires-Dist: python-dotenv
Requires-Dist: chromadb
Requires-Dist: langchain
Requires-Dist: uuid
Requires-Dist: matplotlib
Requires-Dist: wordcloud
